roughset_tools/__init__.py
roughset_tools/roughset.py
roughset_tools_rofilde-0.0.2.dist-info/LICENSE
roughset_tools_rofilde-0.0.2.dist-info/METADATA
roughset_tools_rofilde-0.0.2.dist-info/WHEEL
roughset_tools_rofilde-0.0.2.dist-info/top_level.txt
roughset_tools_rofilde-0.0.2.dist-info/RECORD
