Metadata-Version: 2.1
Name: roughset-tools-rofilde
Version: 0.0.2
Summary: Rough sets implementation in python
Home-page: https://github.com/rhsitorus/roughset-tools
Author: Rofilde Hasudungan
Author-email: rofilde@gmail.com
License: UNKNOWN
Project-URL: Bug Tracker, https://github.com/rhsitorus/roughset-tools/issues
Platform: UNKNOWN
Classifier: Programming Language :: Python :: 3
Classifier: License :: OSI Approved :: MIT License
Classifier: Operating System :: OS Independent
Requires-Python: >=3.6
License-File: LICENSE
